abstractmodels/__init__.py
abstractmodels/py.typed
abstractmodels-0.1.0.dist-info/licenses/LICENSE
abstractmodels-0.1.0.dist-info/METADATA
abstractmodels-0.1.0.dist-info/WHEEL
abstractmodels-0.1.0.dist-info/top_level.txt
abstractmodels-0.1.0.dist-info/RECORD
