Metadata-Version: 2.4
Name: abstractmodels
Version: 0.1.0
Summary: Foundational data models for the AbstractFramework ecosystem
Author: AbstractFramework Contributors
License-Expression: MIT
Project-URL: Homepage, https://github.com/abstractframework/abstractmodels
Project-URL: Documentation, https://github.com/abstractframework/abstractmodels#readme
Project-URL: Repository, https://github.com/abstractframework/abstractmodels
Project-URL: Bug Tracker, https://github.com/abstractframework/abstractmodels/issues
Keywords: abstractframework,models,data-models,schemas,types
Classifier: Development Status :: 3 - Alpha
Classifier: Intended Audience :: Developers
Classifier: Operating System :: OS Independent
Classifier: Programming Language :: Python :: 3
Classifier: Programming Language :: Python :: 3.8
Classifier: Programming Language :: Python :: 3.9
Classifier: Programming Language :: Python :: 3.10
Classifier: Programming Language :: Python :: 3.11
Classifier: Programming Language :: Python :: 3.12
Classifier: Topic :: Software Development :: Libraries :: Python Modules
Classifier: Topic :: Software Development :: Code Generators
Classifier: Typing :: Typed
Requires-Python: >=3.8
License-File: LICENSE
Dynamic: license-file
